{
	"info": {
		"_postman_id": "4e8772b3-04ec-41a2-b708-9dd4628943d2",
		"name": "Task-7",
		"schema": "https://schema.getpostman.com/json/collection/v2.1.0/collection.json",
		"_exporter_id": "31097723"
	},
	"item": [
		{
			"name": "auth",
			"item": [
				{
					"name": "Register",
					"request": {
						"method": "POST",
						"header": [],
						"body": {
							"mode": "raw",
							"raw": "{\r\n    \"name\":\"ahmad\",\r\n    \"email\": \"ahmad@gmail.com\",\r\n    \"age\": 19,\r\n    \"password\": \"12312312345\"\r\n}",
							"options": {
								"raw": {
									"language": "json"
								}
							}
						},
						"url": {
							"raw": "http://localhost:3000/api/register",
							"protocol": "http",
							"host": [
								"localhost"
							],
							"port": "3000",
							"path": [
								"api",
								"register"
							]
						}
					},
					"response": [
						{
							"name": "Register",
							"originalRequest": {
								"method": "POST",
								"header": [],
								"body": {
									"mode": "raw",
									"raw": "{\r\n    \"name\":\"ahmad\",\r\n    \"email\": \"ahmad@gmail.com\",\r\n    \"age\": 19,\r\n    \"password\": \"12312312345\"\r\n}",
									"options": {
										"raw": {
											"language": "json"
										}
									}
								},
								"url": {
									"raw": "http://localhost:3000/api/register",
									"protocol": "http",
									"host": [
										"localhost"
									],
									"port": "3000",
									"path": [
										"api",
										"register"
									]
								}
							},
							"status": "Created",
							"code": 201,
							"_postman_previewlanguage": "json",
							"header": [
								{
									"key": "X-Powered-By",
									"value": "Express"
								},
								{
									"key": "Content-Type",
									"value": "application/json; charset=utf-8"
								},
								{
									"key": "Content-Length",
									"value": "361"
								},
								{
									"key": "ETag",
									"value": "W/\"169-sdMr+ZMpxp5htb8fQWi9hUQu8C4\""
								},
								{
									"key": "Date",
									"value": "Tue, 22 Oct 2024 11:13:28 GMT"
								},
								{
									"key": "Connection",
									"value": "keep-alive"
								},
								{
									"key": "Keep-Alive",
									"value": "timeout=5"
								}
							],
							"cookie": [],
							"body": "{\n    \"token\": \"eyJhbGciOiJIUzI1NiIsInR5cCI6IkpXVCJ9.eyJpZCI6IjY3MTc4OGQ4ZGMxZWU1NThiYzY4MTFlYiIsImlhdCI6MTcyOTU5NTYwOCwiZXhwIjoxNzI5NTk5MjA4fQ.ZPOQE2rCYhPGEDPO_dQvd0NiLfN_RYAPWs-vCdL4iNA\",\n    \"user\": {\n        \"_id\": \"671788d8dc1ee558bc6811eb\",\n        \"name\": \"ahmad\",\n        \"email\": \"ahmad@gmail.com\",\n        \"age\": 19,\n        \"createdAt\": \"2024-10-22T11:13:28.486Z\",\n        \"updatedAt\": \"2024-10-22T11:13:28.486Z\",\n        \"__v\": 0\n    }\n}"
						}
					]
				},
				{
					"name": "Login",
					"request": {
						"method": "POST",
						"header": [],
						"body": {
							"mode": "raw",
							"raw": "{\r\n    \"email\" : \"ahmad@gmail.com\",\r\n    \"password\": \"12312312345\"\r\n}",
							"options": {
								"raw": {
									"language": "json"
								}
							}
						},
						"url": {
							"raw": "http://localhost:3000/api/login",
							"protocol": "http",
							"host": [
								"localhost"
							],
							"port": "3000",
							"path": [
								"api",
								"login"
							]
						}
					},
					"response": [
						{
							"name": "Login",
							"originalRequest": {
								"method": "POST",
								"header": [],
								"body": {
									"mode": "raw",
									"raw": "{\r\n    \"email\" : \"ahmad@gmail.com\",\r\n    \"password\": \"12312312345\"\r\n}",
									"options": {
										"raw": {
											"language": "json"
										}
									}
								},
								"url": {
									"raw": "http://localhost:3000/api/login",
									"protocol": "http",
									"host": [
										"localhost"
									],
									"port": "3000",
									"path": [
										"api",
										"login"
									]
								}
							},
							"status": "OK",
							"code": 200,
							"_postman_previewlanguage": "json",
							"header": [
								{
									"key": "X-Powered-By",
									"value": "Express"
								},
								{
									"key": "Content-Type",
									"value": "application/json; charset=utf-8"
								},
								{
									"key": "Content-Length",
									"value": "386"
								},
								{
									"key": "ETag",
									"value": "W/\"182-U05dx6tJXSYDjzfUq9EQOqxnvOU\""
								},
								{
									"key": "Date",
									"value": "Tue, 22 Oct 2024 11:17:36 GMT"
								},
								{
									"key": "Connection",
									"value": "keep-alive"
								},
								{
									"key": "Keep-Alive",
									"value": "timeout=5"
								}
							],
							"cookie": [],
							"body": "{\n    \"status\": \"login Success\",\n    \"token\": \"eyJhbGciOiJIUzI1NiIsInR5cCI6IkpXVCJ9.eyJpZCI6IjY3MTc4OGQ4ZGMxZWU1NThiYzY4MTFlYiIsImlhdCI6MTcyOTU5NTg1NiwiZXhwIjoxNzI5NTk5NDU2fQ.9qsq7HmSwPj3l9KykQJa7qGEvkHts7oiqg10ogsx1Bg\",\n    \"user\": {\n        \"_id\": \"671788d8dc1ee558bc6811eb\",\n        \"name\": \"ahmad\",\n        \"email\": \"ahmad@gmail.com\",\n        \"age\": 19,\n        \"createdAt\": \"2024-10-22T11:13:28.486Z\",\n        \"updatedAt\": \"2024-10-22T11:13:28.486Z\",\n        \"__v\": 0\n    }\n}"
						}
					]
				},
				{
					"name": "Logout",
					"request": {
						"auth": {
							"type": "bearer",
							"bearer": [
								{
									"key": "token",
									"value": "eyJhbGciOiJIUzI1NiIsInR5cCI6IkpXVCJ9.eyJpZCI6IjY3MTc4OGQ4ZGMxZWU1NThiYzY4MTFlYiIsImlhdCI6MTcyOTU5NTg1NiwiZXhwIjoxNzI5NTk5NDU2fQ.9qsq7HmSwPj3l9KykQJa7qGEvkHts7oiqg10ogsx1Bg",
									"type": "string"
								}
							]
						},
						"method": "POST",
						"header": [],
						"url": {
							"raw": "http://localhost:3000/api/logout",
							"protocol": "http",
							"host": [
								"localhost"
							],
							"port": "3000",
							"path": [
								"api",
								"logout"
							]
						}
					},
					"response": [
						{
							"name": "Logout",
							"originalRequest": {
								"method": "POST",
								"header": [],
								"url": {
									"raw": "http://localhost:3000/api/logout",
									"protocol": "http",
									"host": [
										"localhost"
									],
									"port": "3000",
									"path": [
										"api",
										"logout"
									]
								}
							},
							"status": "OK",
							"code": 200,
							"_postman_previewlanguage": "json",
							"header": [
								{
									"key": "X-Powered-By",
									"value": "Express"
								},
								{
									"key": "Content-Type",
									"value": "application/json; charset=utf-8"
								},
								{
									"key": "Content-Length",
									"value": "33"
								},
								{
									"key": "ETag",
									"value": "W/\"21-lLmD67O0VkKhqUEw0fr9HQ3hNcw\""
								},
								{
									"key": "Date",
									"value": "Tue, 22 Oct 2024 11:20:02 GMT"
								},
								{
									"key": "Connection",
									"value": "keep-alive"
								},
								{
									"key": "Keep-Alive",
									"value": "timeout=5"
								}
							],
							"cookie": [],
							"body": "{\n    \"message\": \"Logout successfully\"\n}"
						}
					]
				}
			]
		},
		{
			"name": "Course",
			"item": [
				{
					"name": "ADD new course",
					"request": {
						"auth": {
							"type": "bearer",
							"bearer": [
								{
									"key": "token",
									"value": "eyJhbGciOiJIUzI1NiIsInR5cCI6IkpXVCJ9.eyJpZCI6IjY3MTc4OGQ4ZGMxZWU1NThiYzY4MTFlYiIsImlhdCI6MTcyOTU5NTg1NiwiZXhwIjoxNzI5NTk5NDU2fQ.9qsq7HmSwPj3l9KykQJa7qGEvkHts7oiqg10ogsx1Bg",
									"type": "string"
								}
							]
						},
						"method": "POST",
						"header": [],
						"body": {
							"mode": "raw",
							"raw": "{\r\n    \"title\": \"Complete c++ Course\",\r\n    \"description\" : \"Introduction to c++\",\r\n    \"Course_Duration\": \"90h\"\r\n}",
							"options": {
								"raw": {
									"language": "json"
								}
							}
						},
						"url": {
							"raw": "http://localhost:3000/api/courses",
							"protocol": "http",
							"host": [
								"localhost"
							],
							"port": "3000",
							"path": [
								"api",
								"courses"
							]
						}
					},
					"response": [
						{
							"name": "ADD new course",
							"originalRequest": {
								"method": "POST",
								"header": [],
								"body": {
									"mode": "raw",
									"raw": "{\r\n    \"title\": \"Complete c++ Course\",\r\n    \"description\" : \"Introduction to c++\",\r\n    \"Course_Duration\": \"90h\"\r\n}",
									"options": {
										"raw": {
											"language": "json"
										}
									}
								},
								"url": {
									"raw": "http://localhost:3000/api/courses",
									"protocol": "http",
									"host": [
										"localhost"
									],
									"port": "3000",
									"path": [
										"api",
										"courses"
									]
								}
							},
							"status": "Created",
							"code": 201,
							"_postman_previewlanguage": "json",
							"header": [
								{
									"key": "X-Powered-By",
									"value": "Express"
								},
								{
									"key": "Content-Type",
									"value": "application/json; charset=utf-8"
								},
								{
									"key": "Content-Length",
									"value": "287"
								},
								{
									"key": "ETag",
									"value": "W/\"11f-PSL4tFu1IF391rz2CbhiXq1ptNA\""
								},
								{
									"key": "Date",
									"value": "Tue, 22 Oct 2024 11:23:21 GMT"
								},
								{
									"key": "Connection",
									"value": "keep-alive"
								},
								{
									"key": "Keep-Alive",
									"value": "timeout=5"
								}
							],
							"cookie": [],
							"body": "{\n    \"status\": \"success\",\n    \"data\": {\n        \"title\": \"Complete c++ Course\",\n        \"description\": \"Introduction to c++\",\n        \"Course_Duration\": \"90h\",\n        \"user_id\": \"671788d8dc1ee558bc6811eb\",\n        \"videos\": [],\n        \"_id\": \"67178b29dc1ee558bc6811f3\",\n        \"createdAt\": \"2024-10-22T11:23:21.592Z\",\n        \"updatedAt\": \"2024-10-22T11:23:21.592Z\",\n        \"__v\": 0\n    }\n}"
						}
					]
				},
				{
					"name": "Get All Courses",
					"request": {
						"auth": {
							"type": "bearer",
							"bearer": [
								{
									"key": "token",
									"value": "eyJhbGciOiJIUzI1NiIsInR5cCI6IkpXVCJ9.eyJpZCI6IjY3MTc4OGQ4ZGMxZWU1NThiYzY4MTFlYiIsImlhdCI6MTcyOTU5NTg1NiwiZXhwIjoxNzI5NTk5NDU2fQ.9qsq7HmSwPj3l9KykQJa7qGEvkHts7oiqg10ogsx1Bg",
									"type": "string"
								}
							]
						},
						"method": "GET",
						"header": [],
						"url": {
							"raw": "http://localhost:3000/api/courses",
							"protocol": "http",
							"host": [
								"localhost"
							],
							"port": "3000",
							"path": [
								"api",
								"courses"
							]
						}
					},
					"response": [
						{
							"name": "Get All Courses",
							"originalRequest": {
								"method": "GET",
								"header": [],
								"url": {
									"raw": "http://localhost:3000/api/courses",
									"protocol": "http",
									"host": [
										"localhost"
									],
									"port": "3000",
									"path": [
										"api",
										"courses"
									]
								}
							},
							"status": "OK",
							"code": 200,
							"_postman_previewlanguage": "json",
							"header": [
								{
									"key": "X-Powered-By",
									"value": "Express"
								},
								{
									"key": "Content-Type",
									"value": "application/json; charset=utf-8"
								},
								{
									"key": "Content-Length",
									"value": "1710"
								},
								{
									"key": "ETag",
									"value": "W/\"6ae-dpRWO3a75k1DO6OYYsoKoa8Uc4U\""
								},
								{
									"key": "Date",
									"value": "Tue, 22 Oct 2024 11:24:36 GMT"
								},
								{
									"key": "Connection",
									"value": "keep-alive"
								},
								{
									"key": "Keep-Alive",
									"value": "timeout=5"
								}
							],
							"cookie": [],
							"body": "{\n    \"status\": \"success\",\n    \"data\": [\n        {\n            \"_id\": \"6713c22721e1b4a09d4d3e19\",\n            \"title\": \"Complete React Course\",\n            \"description\": \"Introduction to React and typescript\",\n            \"Course_Duration\": \"100h\",\n            \"user_id\": {\n                \"_id\": \"670c3378cda14cfdb7e13d06\",\n                \"name\": \"Mootaz\",\n                \"email\": \"mootaz@gmail.com\",\n                \"age\": 120,\n                \"createdAt\": \"2024-10-13T20:54:16.780Z\",\n                \"updatedAt\": \"2024-10-13T20:54:16.780Z\",\n                \"__v\": 0\n            },\n            \"videos\": [\n                {\n                    \"_id\": \"6713cf0791e13d01a30a0871\",\n                    \"title\": \"First Video\",\n                    \"description\": \"What is JSX and components\",\n                    \"course_id\": \"6713c22721e1b4a09d4d3e19\",\n                    \"createdAt\": \"2024-10-19T15:23:51.207Z\",\n                    \"updatedAt\": \"2024-10-19T15:36:27.033Z\",\n                    \"__v\": 0\n                }\n            ],\n            \"createdAt\": \"2024-10-19T14:28:55.277Z\",\n            \"updatedAt\": \"2024-10-21T20:52:09.322Z\",\n            \"__v\": 1\n        },\n        {\n            \"_id\": \"6713c6b8cc82633a02a51d66\",\n            \"title\": \"Complete Angular Course\",\n            \"description\": \"Introduction to Angular\",\n            \"Course_Duration\": \"110h\",\n            \"user_id\": {\n                \"_id\": \"6713ab59798242fb0448265c\",\n                \"name\": \"karem\",\n                \"email\": \"karem@gmail.com\",\n                \"age\": 20,\n                \"createdAt\": \"2024-10-19T12:51:37.861Z\",\n                \"updatedAt\": \"2024-10-19T12:51:37.861Z\",\n                \"__v\": 0\n            },\n            \"videos\": [\n                {\n                    \"_id\": \"6713cd7f91e13d01a30a0856\",\n                    \"title\": \"first video\",\n                    \"description\": \"What is Angular\",\n                    \"course_id\": \"6713c6b8cc82633a02a51d66\",\n                    \"createdAt\": \"2024-10-19T15:17:19.706Z\",\n                    \"updatedAt\": \"2024-10-19T15:17:19.706Z\",\n                    \"__v\": 0\n                }\n            ],\n            \"createdAt\": \"2024-10-19T14:48:24.072Z\",\n            \"updatedAt\": \"2024-10-19T15:20:42.668Z\",\n            \"__v\": 2\n        },\n        {\n            \"_id\": \"67178b29dc1ee558bc6811f3\",\n            \"title\": \"Complete c++ Course\",\n            \"description\": \"Introduction to c++\",\n            \"Course_Duration\": \"90h\",\n            \"user_id\": {\n                \"_id\": \"671788d8dc1ee558bc6811eb\",\n                \"name\": \"ahmad\",\n                \"email\": \"ahmad@gmail.com\",\n                \"age\": 19,\n                \"createdAt\": \"2024-10-22T11:13:28.486Z\",\n                \"updatedAt\": \"2024-10-22T11:13:28.486Z\",\n                \"__v\": 0\n            },\n            \"videos\": [],\n            \"createdAt\": \"2024-10-22T11:23:21.592Z\",\n            \"updatedAt\": \"2024-10-22T11:23:21.592Z\",\n            \"__v\": 0\n        }\n    ]\n}"
						}
					]
				},
				{
					"name": "Get single Course",
					"request": {
						"auth": {
							"type": "bearer",
							"bearer": [
								{
									"key": "token",
									"value": "eyJhbGciOiJIUzI1NiIsInR5cCI6IkpXVCJ9.eyJpZCI6IjY3MTc4OGQ4ZGMxZWU1NThiYzY4MTFlYiIsImlhdCI6MTcyOTU5NTg1NiwiZXhwIjoxNzI5NTk5NDU2fQ.9qsq7HmSwPj3l9KykQJa7qGEvkHts7oiqg10ogsx1Bg",
									"type": "string"
								}
							]
						},
						"method": "GET",
						"header": [],
						"url": {
							"raw": "http://localhost:3000/api/courses/67178b29dc1ee558bc6811f3",
							"protocol": "http",
							"host": [
								"localhost"
							],
							"port": "3000",
							"path": [
								"api",
								"courses",
								"67178b29dc1ee558bc6811f3"
							]
						}
					},
					"response": [
						{
							"name": "Get single Course",
							"originalRequest": {
								"method": "GET",
								"header": [],
								"url": {
									"raw": "http://localhost:3000/api/courses/67178b29dc1ee558bc6811f3",
									"protocol": "http",
									"host": [
										"localhost"
									],
									"port": "3000",
									"path": [
										"api",
										"courses",
										"67178b29dc1ee558bc6811f3"
									]
								}
							},
							"status": "OK",
							"code": 200,
							"_postman_previewlanguage": "json",
							"header": [
								{
									"key": "X-Powered-By",
									"value": "Express"
								},
								{
									"key": "Content-Type",
									"value": "application/json; charset=utf-8"
								},
								{
									"key": "Content-Length",
									"value": "431"
								},
								{
									"key": "ETag",
									"value": "W/\"1af-+v3cwOi3XoI5UiDERZCuts4fvp0\""
								},
								{
									"key": "Date",
									"value": "Tue, 22 Oct 2024 11:26:32 GMT"
								},
								{
									"key": "Connection",
									"value": "keep-alive"
								},
								{
									"key": "Keep-Alive",
									"value": "timeout=5"
								}
							],
							"cookie": [],
							"body": "{\n    \"status\": \"success\",\n    \"data\": {\n        \"_id\": \"67178b29dc1ee558bc6811f3\",\n        \"title\": \"Complete c++ Course\",\n        \"description\": \"Introduction to c++\",\n        \"Course_Duration\": \"90h\",\n        \"user_id\": {\n            \"_id\": \"671788d8dc1ee558bc6811eb\",\n            \"name\": \"ahmad\",\n            \"email\": \"ahmad@gmail.com\",\n            \"age\": 19,\n            \"createdAt\": \"2024-10-22T11:13:28.486Z\",\n            \"updatedAt\": \"2024-10-22T11:13:28.486Z\",\n            \"__v\": 0\n        },\n        \"videos\": [],\n        \"createdAt\": \"2024-10-22T11:23:21.592Z\",\n        \"updatedAt\": \"2024-10-22T11:23:21.592Z\",\n        \"__v\": 0\n    }\n}"
						}
					]
				},
				{
					"name": "Edit Course",
					"request": {
						"auth": {
							"type": "bearer",
							"bearer": [
								{
									"key": "token",
									"value": "eyJhbGciOiJIUzI1NiIsInR5cCI6IkpXVCJ9.eyJpZCI6IjY3MTc4OGQ4ZGMxZWU1NThiYzY4MTFlYiIsImlhdCI6MTcyOTU5NTg1NiwiZXhwIjoxNzI5NTk5NDU2fQ.9qsq7HmSwPj3l9KykQJa7qGEvkHts7oiqg10ogsx1Bg",
									"type": "string"
								}
							]
						},
						"method": "PUT",
						"header": [],
						"body": {
							"mode": "raw",
							"raw": "{\r\n    \"title\": \"Complete c++ Course\",\r\n    \"description\" : \"Introduction to c++ and OOP\",\r\n    \"Course_Duration\": \"90h\"\r\n}",
							"options": {
								"raw": {
									"language": "json"
								}
							}
						},
						"url": {
							"raw": "http://localhost:3000/api/courses/67178b29dc1ee558bc6811f3",
							"protocol": "http",
							"host": [
								"localhost"
							],
							"port": "3000",
							"path": [
								"api",
								"courses",
								"67178b29dc1ee558bc6811f3"
							]
						}
					},
					"response": [
						{
							"name": "Edit Course",
							"originalRequest": {
								"method": "PUT",
								"header": [],
								"body": {
									"mode": "raw",
									"raw": "{\r\n    \"title\": \"Complete c++ Course\",\r\n    \"description\" : \"Introduction to c++ and OOP\",\r\n    \"Course_Duration\": \"90h\"\r\n}",
									"options": {
										"raw": {
											"language": "json"
										}
									}
								},
								"url": {
									"raw": "http://localhost:3000/api/courses/67178b29dc1ee558bc6811f3",
									"protocol": "http",
									"host": [
										"localhost"
									],
									"port": "3000",
									"path": [
										"api",
										"courses",
										"67178b29dc1ee558bc6811f3"
									]
								}
							},
							"status": "OK",
							"code": 200,
							"_postman_previewlanguage": "json",
							"header": [
								{
									"key": "X-Powered-By",
									"value": "Express"
								},
								{
									"key": "Content-Type",
									"value": "application/json; charset=utf-8"
								},
								{
									"key": "Content-Length",
									"value": "295"
								},
								{
									"key": "ETag",
									"value": "W/\"127-VVEmsdzoqWJjhGOt1hjkNmN1CzQ\""
								},
								{
									"key": "Date",
									"value": "Tue, 22 Oct 2024 11:29:30 GMT"
								},
								{
									"key": "Connection",
									"value": "keep-alive"
								},
								{
									"key": "Keep-Alive",
									"value": "timeout=5"
								}
							],
							"cookie": [],
							"body": "{\n    \"status\": \"success\",\n    \"data\": {\n        \"_id\": \"67178b29dc1ee558bc6811f3\",\n        \"title\": \"Complete c++ Course\",\n        \"description\": \"Introduction to c++ and OOP\",\n        \"Course_Duration\": \"90h\",\n        \"user_id\": \"671788d8dc1ee558bc6811eb\",\n        \"videos\": [],\n        \"createdAt\": \"2024-10-22T11:23:21.592Z\",\n        \"updatedAt\": \"2024-10-22T11:29:30.221Z\",\n        \"__v\": 0\n    }\n}"
						}
					]
				},
				{
					"name": "Delete Course",
					"request": {
						"auth": {
							"type": "bearer",
							"bearer": [
								{
									"key": "token",
									"value": "eyJhbGciOiJIUzI1NiIsInR5cCI6IkpXVCJ9.eyJpZCI6IjY3MTc4OGQ4ZGMxZWU1NThiYzY4MTFlYiIsImlhdCI6MTcyOTU5NTg1NiwiZXhwIjoxNzI5NTk5NDU2fQ.9qsq7HmSwPj3l9KykQJa7qGEvkHts7oiqg10ogsx1Bg",
									"type": "string"
								}
							]
						},
						"method": "DELETE",
						"header": [],
						"url": {
							"raw": "http://localhost:3000/api/courses/67178b29dc1ee558bc6811f3",
							"protocol": "http",
							"host": [
								"localhost"
							],
							"port": "3000",
							"path": [
								"api",
								"courses",
								"67178b29dc1ee558bc6811f3"
							]
						}
					},
					"response": [
						{
							"name": "Delete Course",
							"originalRequest": {
								"method": "DELETE",
								"header": [],
								"url": {
									"raw": "http://localhost:3000/api/courses/67178b29dc1ee558bc6811f3",
									"protocol": "http",
									"host": [
										"localhost"
									],
									"port": "3000",
									"path": [
										"api",
										"courses",
										"67178b29dc1ee558bc6811f3"
									]
								}
							},
							"status": "OK",
							"code": 200,
							"_postman_previewlanguage": "json",
							"header": [
								{
									"key": "X-Powered-By",
									"value": "Express"
								},
								{
									"key": "Content-Type",
									"value": "application/json; charset=utf-8"
								},
								{
									"key": "Content-Length",
									"value": "20"
								},
								{
									"key": "ETag",
									"value": "W/\"14-Y53wuE/mmbSikKcT/WualL1N65U\""
								},
								{
									"key": "Date",
									"value": "Tue, 22 Oct 2024 11:45:37 GMT"
								},
								{
									"key": "Connection",
									"value": "keep-alive"
								},
								{
									"key": "Keep-Alive",
									"value": "timeout=5"
								}
							],
							"cookie": [],
							"body": "{\n    \"status\": \"success\"\n}"
						}
					]
				}
			]
		},
		{
			"name": "Video",
			"item": [
				{
					"name": "Add Video",
					"request": {
						"auth": {
							"type": "bearer",
							"bearer": [
								{
									"key": "token",
									"value": "eyJhbGciOiJIUzI1NiIsInR5cCI6IkpXVCJ9.eyJpZCI6IjY3MTc4OGQ4ZGMxZWU1NThiYzY4MTFlYiIsImlhdCI6MTcyOTU5NTg1NiwiZXhwIjoxNzI5NTk5NDU2fQ.9qsq7HmSwPj3l9KykQJa7qGEvkHts7oiqg10ogsx1Bg",
									"type": "string"
								}
							]
						},
						"method": "POST",
						"header": [],
						"body": {
							"mode": "raw",
							"raw": "{\r\n    \"title\": \"First Video\",\r\n    \"description\": \"What is c++\",\r\n    \"course_id\": \"67178b29dc1ee558bc6811f3\"\r\n}",
							"options": {
								"raw": {
									"language": "json"
								}
							}
						},
						"url": {
							"raw": "http://localhost:3000/api/videos",
							"protocol": "http",
							"host": [
								"localhost"
							],
							"port": "3000",
							"path": [
								"api",
								"videos"
							]
						}
					},
					"response": [
						{
							"name": "Add Video",
							"originalRequest": {
								"method": "POST",
								"header": [],
								"body": {
									"mode": "raw",
									"raw": "{\r\n    \"title\": \"First Video\",\r\n    \"description\": \"What is c++\",\r\n    \"course_id\": \"67178b29dc1ee558bc6811f3\"\r\n}",
									"options": {
										"raw": {
											"language": "json"
										}
									}
								},
								"url": {
									"raw": "http://localhost:3000/api/videos",
									"protocol": "http",
									"host": [
										"localhost"
									],
									"port": "3000",
									"path": [
										"api",
										"videos"
									]
								}
							},
							"status": "Created",
							"code": 201,
							"_postman_previewlanguage": "json",
							"header": [
								{
									"key": "X-Powered-By",
									"value": "Express"
								},
								{
									"key": "Content-Type",
									"value": "application/json; charset=utf-8"
								},
								{
									"key": "Content-Length",
									"value": "237"
								},
								{
									"key": "ETag",
									"value": "W/\"ed-CEAhojAYpCLkmNaJAwq0ZrwqRFE\""
								},
								{
									"key": "Date",
									"value": "Tue, 22 Oct 2024 11:33:24 GMT"
								},
								{
									"key": "Connection",
									"value": "keep-alive"
								},
								{
									"key": "Keep-Alive",
									"value": "timeout=5"
								}
							],
							"cookie": [],
							"body": "{\n    \"status\": \"success\",\n    \"data\": {\n        \"title\": \"First Video\",\n        \"description\": \"What is c++\",\n        \"course_id\": \"67178b29dc1ee558bc6811f3\",\n        \"_id\": \"67178d84a92b9ede147b5fb2\",\n        \"createdAt\": \"2024-10-22T11:33:24.817Z\",\n        \"updatedAt\": \"2024-10-22T11:33:24.817Z\",\n        \"__v\": 0\n    }\n}"
						}
					]
				},
				{
					"name": "Get All Video",
					"request": {
						"auth": {
							"type": "bearer",
							"bearer": [
								{
									"key": "token",
									"value": "eyJhbGciOiJIUzI1NiIsInR5cCI6IkpXVCJ9.eyJpZCI6IjY3MTc4OGQ4ZGMxZWU1NThiYzY4MTFlYiIsImlhdCI6MTcyOTU5NTg1NiwiZXhwIjoxNzI5NTk5NDU2fQ.9qsq7HmSwPj3l9KykQJa7qGEvkHts7oiqg10ogsx1Bg",
									"type": "string"
								}
							]
						},
						"method": "GET",
						"header": [],
						"url": {
							"raw": "http://localhost:3000/api/videos",
							"protocol": "http",
							"host": [
								"localhost"
							],
							"port": "3000",
							"path": [
								"api",
								"videos"
							]
						}
					},
					"response": [
						{
							"name": "Get All Video",
							"originalRequest": {
								"method": "GET",
								"header": [],
								"url": {
									"raw": "http://localhost:3000/api/videos",
									"protocol": "http",
									"host": [
										"localhost"
									],
									"port": "3000",
									"path": [
										"api",
										"videos"
									]
								}
							},
							"status": "OK",
							"code": 200,
							"_postman_previewlanguage": "json",
							"header": [
								{
									"key": "X-Powered-By",
									"value": "Express"
								},
								{
									"key": "Content-Type",
									"value": "application/json; charset=utf-8"
								},
								{
									"key": "Content-Length",
									"value": "1519"
								},
								{
									"key": "ETag",
									"value": "W/\"5ef-5aBH0sjaDRtaTPA7jWjqtSTZwWw\""
								},
								{
									"key": "Date",
									"value": "Tue, 22 Oct 2024 11:35:33 GMT"
								},
								{
									"key": "Connection",
									"value": "keep-alive"
								},
								{
									"key": "Keep-Alive",
									"value": "timeout=5"
								}
							],
							"cookie": [],
							"body": "{\n    \"status\": \"success\",\n    \"data\": [\n        {\n            \"_id\": \"6713cd7f91e13d01a30a0856\",\n            \"title\": \"first video\",\n            \"description\": \"What is Angular\",\n            \"course_id\": {\n                \"_id\": \"6713c6b8cc82633a02a51d66\",\n                \"title\": \"Complete Angular Course\",\n                \"description\": \"Introduction to Angular\",\n                \"Course_Duration\": \"110h\",\n                \"user_id\": \"6713ab59798242fb0448265c\",\n                \"videos\": [\n                    \"6713cd7f91e13d01a30a0856\",\n                    \"6713ce4a91e13d01a30a0863\"\n                ],\n                \"createdAt\": \"2024-10-19T14:48:24.072Z\",\n                \"updatedAt\": \"2024-10-19T15:20:42.668Z\",\n                \"__v\": 2\n            },\n            \"createdAt\": \"2024-10-19T15:17:19.706Z\",\n            \"updatedAt\": \"2024-10-19T15:17:19.706Z\",\n            \"__v\": 0\n        },\n        {\n            \"_id\": \"6713cf0791e13d01a30a0871\",\n            \"title\": \"First Video\",\n            \"description\": \"What is JSX and components\",\n            \"course_id\": {\n                \"_id\": \"6713c22721e1b4a09d4d3e19\",\n                \"title\": \"Complete React Course\",\n                \"description\": \"Introduction to React and typescript\",\n                \"Course_Duration\": \"100h\",\n                \"user_id\": \"670c3378cda14cfdb7e13d06\",\n                \"videos\": [\n                    \"6713cf0791e13d01a30a0871\"\n                ],\n                \"createdAt\": \"2024-10-19T14:28:55.277Z\",\n                \"updatedAt\": \"2024-10-21T20:52:09.322Z\",\n                \"__v\": 1\n            },\n            \"createdAt\": \"2024-10-19T15:23:51.207Z\",\n            \"updatedAt\": \"2024-10-19T15:36:27.033Z\",\n            \"__v\": 0\n        },\n        {\n            \"_id\": \"67178d84a92b9ede147b5fb2\",\n            \"title\": \"First Video\",\n            \"description\": \"What is c++\",\n            \"course_id\": {\n                \"_id\": \"67178b29dc1ee558bc6811f3\",\n                \"title\": \"Complete c++ Course\",\n                \"description\": \"Introduction to c++ and OOP\",\n                \"Course_Duration\": \"95h\",\n                \"user_id\": \"671788d8dc1ee558bc6811eb\",\n                \"videos\": [\n                    \"67178d84a92b9ede147b5fb2\"\n                ],\n                \"createdAt\": \"2024-10-22T11:23:21.592Z\",\n                \"updatedAt\": \"2024-10-22T11:34:50.362Z\",\n                \"__v\": 1\n            },\n            \"createdAt\": \"2024-10-22T11:33:24.817Z\",\n            \"updatedAt\": \"2024-10-22T11:33:24.817Z\",\n            \"__v\": 0\n        }\n    ]\n}"
						}
					]
				},
				{
					"name": "Get single Video",
					"request": {
						"auth": {
							"type": "bearer",
							"bearer": [
								{
									"key": "token",
									"value": "eyJhbGciOiJIUzI1NiIsInR5cCI6IkpXVCJ9.eyJpZCI6IjY3MTc4OGQ4ZGMxZWU1NThiYzY4MTFlYiIsImlhdCI6MTcyOTU5NTg1NiwiZXhwIjoxNzI5NTk5NDU2fQ.9qsq7HmSwPj3l9KykQJa7qGEvkHts7oiqg10ogsx1Bg",
									"type": "string"
								}
							]
						},
						"method": "GET",
						"header": [],
						"url": {
							"raw": "http://localhost:3000/api/videos/67178d84a92b9ede147b5fb2",
							"protocol": "http",
							"host": [
								"localhost"
							],
							"port": "3000",
							"path": [
								"api",
								"videos",
								"67178d84a92b9ede147b5fb2"
							]
						}
					},
					"response": [
						{
							"name": "Get single Video",
							"originalRequest": {
								"method": "GET",
								"header": [],
								"url": {
									"raw": "http://localhost:3000/api/videos/67178d84a92b9ede147b5fb2",
									"protocol": "http",
									"host": [
										"localhost"
									],
									"port": "3000",
									"path": [
										"api",
										"videos",
										"67178d84a92b9ede147b5fb2"
									]
								}
							},
							"status": "OK",
							"code": 200,
							"_postman_previewlanguage": "json",
							"header": [
								{
									"key": "X-Powered-By",
									"value": "Express"
								},
								{
									"key": "Content-Type",
									"value": "application/json; charset=utf-8"
								},
								{
									"key": "Content-Length",
									"value": "504"
								},
								{
									"key": "ETag",
									"value": "W/\"1f8-5MXNYSsPsyNdoFkyG2bxv3Qjkl0\""
								},
								{
									"key": "Date",
									"value": "Tue, 22 Oct 2024 11:36:51 GMT"
								},
								{
									"key": "Connection",
									"value": "keep-alive"
								},
								{
									"key": "Keep-Alive",
									"value": "timeout=5"
								}
							],
							"cookie": [],
							"body": "{\n    \"status\": \"success\",\n    \"data\": {\n        \"_id\": \"67178d84a92b9ede147b5fb2\",\n        \"title\": \"First Video\",\n        \"description\": \"What is c++\",\n        \"course_id\": {\n            \"_id\": \"67178b29dc1ee558bc6811f3\",\n            \"title\": \"Complete c++ Course\",\n            \"description\": \"Introduction to c++ and OOP\",\n            \"Course_Duration\": \"95h\",\n            \"user_id\": \"671788d8dc1ee558bc6811eb\",\n            \"videos\": [\n                \"67178d84a92b9ede147b5fb2\"\n            ],\n            \"createdAt\": \"2024-10-22T11:23:21.592Z\",\n            \"updatedAt\": \"2024-10-22T11:34:50.362Z\",\n            \"__v\": 1\n        },\n        \"createdAt\": \"2024-10-22T11:33:24.817Z\",\n        \"updatedAt\": \"2024-10-22T11:33:24.817Z\",\n        \"__v\": 0\n    }\n}"
						}
					]
				},
				{
					"name": "Edit Video",
					"request": {
						"auth": {
							"type": "bearer",
							"bearer": [
								{
									"key": "token",
									"value": "eyJhbGciOiJIUzI1NiIsInR5cCI6IkpXVCJ9.eyJpZCI6IjY3MTc4OGQ4ZGMxZWU1NThiYzY4MTFlYiIsImlhdCI6MTcyOTU5NTg1NiwiZXhwIjoxNzI5NTk5NDU2fQ.9qsq7HmSwPj3l9KykQJa7qGEvkHts7oiqg10ogsx1Bg",
									"type": "string"
								}
							]
						},
						"method": "PUT",
						"header": [],
						"body": {
							"mode": "raw",
							"raw": "{\r\n    \"title\": \"First Video\",\r\n    \"description\": \"What is c++ and OOP\",\r\n    \"course_id\": \"67178b29dc1ee558bc6811f3\"\r\n}",
							"options": {
								"raw": {
									"language": "json"
								}
							}
						},
						"url": {
							"raw": "http://localhost:3000/api/videos/67178d84a92b9ede147b5fb2",
							"protocol": "http",
							"host": [
								"localhost"
							],
							"port": "3000",
							"path": [
								"api",
								"videos",
								"67178d84a92b9ede147b5fb2"
							]
						}
					},
					"response": [
						{
							"name": "Edit Video",
							"originalRequest": {
								"method": "PUT",
								"header": [],
								"body": {
									"mode": "raw",
									"raw": "{\r\n    \"title\": \"First Video\",\r\n    \"description\": \"What is c++ and OOP\",\r\n    \"course_id\": \"67178b29dc1ee558bc6811f3\"\r\n}",
									"options": {
										"raw": {
											"language": "json"
										}
									}
								},
								"url": {
									"raw": "http://localhost:3000/api/videos/67178d84a92b9ede147b5fb2",
									"protocol": "http",
									"host": [
										"localhost"
									],
									"port": "3000",
									"path": [
										"api",
										"videos",
										"67178d84a92b9ede147b5fb2"
									]
								}
							},
							"status": "OK",
							"code": 200,
							"_postman_previewlanguage": "json",
							"header": [
								{
									"key": "X-Powered-By",
									"value": "Express"
								},
								{
									"key": "Content-Type",
									"value": "application/json; charset=utf-8"
								},
								{
									"key": "Content-Length",
									"value": "245"
								},
								{
									"key": "ETag",
									"value": "W/\"f5-GO+KtdPqsKGBgmWDDoAj8H62Jgw\""
								},
								{
									"key": "Date",
									"value": "Tue, 22 Oct 2024 11:40:57 GMT"
								},
								{
									"key": "Connection",
									"value": "keep-alive"
								},
								{
									"key": "Keep-Alive",
									"value": "timeout=5"
								}
							],
							"cookie": [],
							"body": "{\n    \"status\": \"success\",\n    \"data\": {\n        \"_id\": \"67178d84a92b9ede147b5fb2\",\n        \"title\": \"First Video\",\n        \"description\": \"What is c++ and OOP\",\n        \"course_id\": \"67178b29dc1ee558bc6811f3\",\n        \"createdAt\": \"2024-10-22T11:33:24.817Z\",\n        \"updatedAt\": \"2024-10-22T11:40:57.524Z\",\n        \"__v\": 0\n    }\n}"
						}
					]
				},
				{
					"name": "Delete Video",
					"request": {
						"auth": {
							"type": "bearer",
							"bearer": [
								{
									"key": "token",
									"value": "eyJhbGciOiJIUzI1NiIsInR5cCI6IkpXVCJ9.eyJpZCI6IjY3MTc4OGQ4ZGMxZWU1NThiYzY4MTFlYiIsImlhdCI6MTcyOTU5NTg1NiwiZXhwIjoxNzI5NTk5NDU2fQ.9qsq7HmSwPj3l9KykQJa7qGEvkHts7oiqg10ogsx1Bg",
									"type": "string"
								}
							]
						},
						"method": "DELETE",
						"header": [],
						"body": {
							"mode": "raw",
							"raw": "{\r\n    \"course_id\": \"67178b29dc1ee558bc6811f3\"\r\n}",
							"options": {
								"raw": {
									"language": "json"
								}
							}
						},
						"url": {
							"raw": "http://localhost:3000/api/videos/67178f85a92b9ede147b5fda",
							"protocol": "http",
							"host": [
								"localhost"
							],
							"port": "3000",
							"path": [
								"api",
								"videos",
								"67178f85a92b9ede147b5fda"
							]
						}
					},
					"response": [
						{
							"name": "Delete Video",
							"originalRequest": {
								"method": "DELETE",
								"header": [],
								"body": {
									"mode": "raw",
									"raw": "{\r\n    \"course_id\": \"67178b29dc1ee558bc6811f3\"\r\n}",
									"options": {
										"raw": {
											"language": "json"
										}
									}
								},
								"url": {
									"raw": "http://localhost:3000/api/videos/67178f85a92b9ede147b5fda",
									"protocol": "http",
									"host": [
										"localhost"
									],
									"port": "3000",
									"path": [
										"api",
										"videos",
										"67178f85a92b9ede147b5fda"
									]
								}
							},
							"status": "OK",
							"code": 200,
							"_postman_previewlanguage": "json",
							"header": [
								{
									"key": "X-Powered-By",
									"value": "Express"
								},
								{
									"key": "Content-Type",
									"value": "application/json; charset=utf-8"
								},
								{
									"key": "Content-Length",
									"value": "20"
								},
								{
									"key": "ETag",
									"value": "W/\"14-Y53wuE/mmbSikKcT/WualL1N65U\""
								},
								{
									"key": "Date",
									"value": "Tue, 22 Oct 2024 11:43:11 GMT"
								},
								{
									"key": "Connection",
									"value": "keep-alive"
								},
								{
									"key": "Keep-Alive",
									"value": "timeout=5"
								}
							],
							"cookie": [],
							"body": "{\n    \"status\": \"success\"\n}"
						}
					]
				}
			]
		},
		{
			"name": "Comment",
			"item": [
				{
					"name": "Add Comment",
					"request": {
						"auth": {
							"type": "bearer",
							"bearer": [
								{
									"key": "token",
									"value": "eyJhbGciOiJIUzI1NiIsInR5cCI6IkpXVCJ9.eyJpZCI6IjY3MTc4OGQ4ZGMxZWU1NThiYzY4MTFlYiIsImlhdCI6MTcyOTU5NTg1NiwiZXhwIjoxNzI5NTk5NDU2fQ.9qsq7HmSwPj3l9KykQJa7qGEvkHts7oiqg10ogsx1Bg",
									"type": "string"
								}
							]
						},
						"method": "POST",
						"header": [],
						"body": {
							"mode": "raw",
							"raw": "{\r\n    \"text\": \"This A perfect content and i love it\",\r\n    \"video_id\": \"6713cf0791e13d01a30a0871\"\r\n}",
							"options": {
								"raw": {
									"language": "json"
								}
							}
						},
						"url": {
							"raw": "http://localhost:3000/api/comments",
							"protocol": "http",
							"host": [
								"localhost"
							],
							"port": "3000",
							"path": [
								"api",
								"comments"
							]
						}
					},
					"response": [
						{
							"name": "Add Comment",
							"originalRequest": {
								"method": "POST",
								"header": [],
								"body": {
									"mode": "raw",
									"raw": "{\r\n    \"text\": \"This A perfect content and i love it\",\r\n    \"video_id\": \"6713cf0791e13d01a30a0871\"\r\n}",
									"options": {
										"raw": {
											"language": "json"
										}
									}
								},
								"url": {
									"raw": "http://localhost:3000/api/comments",
									"protocol": "http",
									"host": [
										"localhost"
									],
									"port": "3000",
									"path": [
										"api",
										"comments"
									]
								}
							},
							"status": "Created",
							"code": 201,
							"_postman_previewlanguage": "json",
							"header": [
								{
									"key": "X-Powered-By",
									"value": "Express"
								},
								{
									"key": "Content-Type",
									"value": "application/json; charset=utf-8"
								},
								{
									"key": "Content-Length",
									"value": "232"
								},
								{
									"key": "ETag",
									"value": "W/\"e8-lTEVv9W35mG/l1b96vpYr5yvLMQ\""
								},
								{
									"key": "Date",
									"value": "Tue, 22 Oct 2024 11:49:36 GMT"
								},
								{
									"key": "Connection",
									"value": "keep-alive"
								},
								{
									"key": "Keep-Alive",
									"value": "timeout=5"
								}
							],
							"cookie": [],
							"body": "{\n    \"status\": \"success\",\n    \"data\": {\n        \"text\": \"This A perfect content and i love it\",\n        \"video_id\": \"6713cf0791e13d01a30a0871\",\n        \"_id\": \"671791508a5fc450e1db35ee\",\n        \"createdAt\": \"2024-10-22T11:49:36.824Z\",\n        \"updatedAt\": \"2024-10-22T11:49:36.824Z\",\n        \"__v\": 0\n    }\n}"
						}
					]
				},
				{
					"name": "Get all comments",
					"request": {
						"auth": {
							"type": "bearer",
							"bearer": [
								{
									"key": "token",
									"value": "eyJhbGciOiJIUzI1NiIsInR5cCI6IkpXVCJ9.eyJpZCI6IjY3MTc4OGQ4ZGMxZWU1NThiYzY4MTFlYiIsImlhdCI6MTcyOTU5OTk0NCwiZXhwIjoxNzI5NjAzNTQ0fQ.bXj82tFXdh01oXHjr-SE8faRvJg6xxGnqA45duGWdYQ",
									"type": "string"
								}
							]
						},
						"method": "GET",
						"header": [],
						"url": {
							"raw": "http://localhost:3000/api/comments",
							"protocol": "http",
							"host": [
								"localhost"
							],
							"port": "3000",
							"path": [
								"api",
								"comments"
							]
						}
					},
					"response": [
						{
							"name": "Get all comments",
							"originalRequest": {
								"method": "GET",
								"header": [],
								"url": {
									"raw": "http://localhost:3000/api/comments",
									"protocol": "http",
									"host": [
										"localhost"
									],
									"port": "3000",
									"path": [
										"api",
										"comments"
									]
								}
							},
							"status": "OK",
							"code": 200,
							"_postman_previewlanguage": "json",
							"header": [
								{
									"key": "X-Powered-By",
									"value": "Express"
								},
								{
									"key": "Content-Type",
									"value": "application/json; charset=utf-8"
								},
								{
									"key": "Content-Length",
									"value": "1733"
								},
								{
									"key": "ETag",
									"value": "W/\"6c5-mavNmByO9L13TlG3RQ34330Pldw\""
								},
								{
									"key": "Date",
									"value": "Tue, 22 Oct 2024 12:34:24 GMT"
								},
								{
									"key": "Connection",
									"value": "keep-alive"
								},
								{
									"key": "Keep-Alive",
									"value": "timeout=5"
								}
							],
							"cookie": [],
							"body": "{\n    \"status\": \"success\",\n    \"data\": [\n        {\n            \"_id\": \"67179500b44a8e1aff8e8193\",\n            \"text\": \"This A perfect content and i love it\",\n            \"video_id\": {\n                \"_id\": \"6713cf0791e13d01a30a0871\",\n                \"title\": \"First Video\",\n                \"description\": \"What is JSX and components\",\n                \"course_id\": \"6713c22721e1b4a09d4d3e19\",\n                \"createdAt\": \"2024-10-19T15:23:51.207Z\",\n                \"updatedAt\": \"2024-10-19T15:36:27.033Z\",\n                \"__v\": 0\n            },\n            \"user_id\": {\n                \"_id\": \"671788d8dc1ee558bc6811eb\",\n                \"name\": \"ahmad\",\n                \"email\": \"ahmad@gmail.com\",\n                \"age\": 19,\n                \"createdAt\": \"2024-10-22T11:13:28.486Z\",\n                \"updatedAt\": \"2024-10-22T11:13:28.486Z\",\n                \"__v\": 0\n            },\n            \"createdAt\": \"2024-10-22T12:05:20.259Z\",\n            \"updatedAt\": \"2024-10-22T12:05:20.259Z\",\n            \"__v\": 0\n        },\n        {\n            \"_id\": \"67179511b44a8e1aff8e8197\",\n            \"text\": \"Thanks\",\n            \"video_id\": {\n                \"_id\": \"6713cf0791e13d01a30a0871\",\n                \"title\": \"First Video\",\n                \"description\": \"What is JSX and components\",\n                \"course_id\": \"6713c22721e1b4a09d4d3e19\",\n                \"createdAt\": \"2024-10-19T15:23:51.207Z\",\n                \"updatedAt\": \"2024-10-19T15:36:27.033Z\",\n                \"__v\": 0\n            },\n            \"user_id\": {\n                \"_id\": \"671788d8dc1ee558bc6811eb\",\n                \"name\": \"ahmad\",\n                \"email\": \"ahmad@gmail.com\",\n                \"age\": 19,\n                \"createdAt\": \"2024-10-22T11:13:28.486Z\",\n                \"updatedAt\": \"2024-10-22T11:13:28.486Z\",\n                \"__v\": 0\n            },\n            \"createdAt\": \"2024-10-22T12:05:37.081Z\",\n            \"updatedAt\": \"2024-10-22T12:05:37.081Z\",\n            \"__v\": 0\n        },\n        {\n            \"_id\": \"67179abaee5cf2d94511d618\",\n            \"text\": \"This A perfect content ❤\",\n            \"video_id\": {\n                \"_id\": \"6713cd7f91e13d01a30a0856\",\n                \"title\": \"first video\",\n                \"description\": \"What is Angular\",\n                \"course_id\": \"6713c6b8cc82633a02a51d66\",\n                \"createdAt\": \"2024-10-19T15:17:19.706Z\",\n                \"updatedAt\": \"2024-10-19T15:17:19.706Z\",\n                \"__v\": 0\n            },\n            \"user_id\": {\n                \"_id\": \"670c3378cda14cfdb7e13d06\",\n                \"name\": \"Mootaz\",\n                \"email\": \"mootaz@gmail.com\",\n                \"age\": 120,\n                \"createdAt\": \"2024-10-13T20:54:16.780Z\",\n                \"updatedAt\": \"2024-10-13T20:54:16.780Z\",\n                \"__v\": 0\n            },\n            \"createdAt\": \"2024-10-22T12:29:46.114Z\",\n            \"updatedAt\": \"2024-10-22T12:30:53.165Z\",\n            \"__v\": 0\n        }\n    ]\n}"
						}
					]
				},
				{
					"name": "Get single Comments",
					"request": {
						"auth": {
							"type": "bearer",
							"bearer": [
								{
									"key": "token",
									"value": "eyJhbGciOiJIUzI1NiIsInR5cCI6IkpXVCJ9.eyJpZCI6IjY3MTc4OGQ4ZGMxZWU1NThiYzY4MTFlYiIsImlhdCI6MTcyOTU5OTk0NCwiZXhwIjoxNzI5NjAzNTQ0fQ.bXj82tFXdh01oXHjr-SE8faRvJg6xxGnqA45duGWdYQ",
									"type": "string"
								}
							]
						},
						"method": "GET",
						"header": [],
						"url": {
							"raw": "http://localhost:3000/api/comments/67179500b44a8e1aff8e8193",
							"protocol": "http",
							"host": [
								"localhost"
							],
							"port": "3000",
							"path": [
								"api",
								"comments",
								"67179500b44a8e1aff8e8193"
							]
						}
					},
					"response": [
						{
							"name": "Get single Comments",
							"originalRequest": {
								"method": "GET",
								"header": [],
								"url": {
									"raw": "http://localhost:3000/api/comments/67179500b44a8e1aff8e8193",
									"protocol": "http",
									"host": [
										"localhost"
									],
									"port": "3000",
									"path": [
										"api",
										"comments",
										"67179500b44a8e1aff8e8193"
									]
								}
							},
							"status": "OK",
							"code": 200,
							"_postman_previewlanguage": "json",
							"header": [
								{
									"key": "X-Powered-By",
									"value": "Express"
								},
								{
									"key": "Content-Type",
									"value": "application/json; charset=utf-8"
								},
								{
									"key": "Content-Length",
									"value": "467"
								},
								{
									"key": "ETag",
									"value": "W/\"1d3-m2CEIwNdczWgyom205yQY9Fkr3o\""
								},
								{
									"key": "Date",
									"value": "Tue, 22 Oct 2024 12:35:12 GMT"
								},
								{
									"key": "Connection",
									"value": "keep-alive"
								},
								{
									"key": "Keep-Alive",
									"value": "timeout=5"
								}
							],
							"cookie": [],
							"body": "{\n    \"status\": \"success\",\n    \"data\": {\n        \"_id\": \"67179500b44a8e1aff8e8193\",\n        \"text\": \"This A perfect content and i love it\",\n        \"video_id\": {\n            \"_id\": \"6713cf0791e13d01a30a0871\",\n            \"title\": \"First Video\",\n            \"description\": \"What is JSX and components\",\n            \"course_id\": \"6713c22721e1b4a09d4d3e19\",\n            \"createdAt\": \"2024-10-19T15:23:51.207Z\",\n            \"updatedAt\": \"2024-10-19T15:36:27.033Z\",\n            \"__v\": 0\n        },\n        \"user_id\": \"671788d8dc1ee558bc6811eb\",\n        \"createdAt\": \"2024-10-22T12:05:20.259Z\",\n        \"updatedAt\": \"2024-10-22T12:05:20.259Z\",\n        \"__v\": 0\n    }\n}"
						}
					]
				},
				{
					"name": "update Comment",
					"request": {
						"auth": {
							"type": "bearer",
							"bearer": [
								{
									"key": "token",
									"value": "eyJhbGciOiJIUzI1NiIsInR5cCI6IkpXVCJ9.eyJpZCI6IjY3MTc4OGQ4ZGMxZWU1NThiYzY4MTFlYiIsImlhdCI6MTcyOTU5OTk0NCwiZXhwIjoxNzI5NjAzNTQ0fQ.bXj82tFXdh01oXHjr-SE8faRvJg6xxGnqA45duGWdYQ",
									"type": "string"
								}
							]
						},
						"method": "PUT",
						"header": [],
						"body": {
							"mode": "raw",
							"raw": "{\r\n    \"text\": \"This A perfect content \",\r\n    \"video_id\": \"6713cf0791e13d01a30a0871\"\r\n}",
							"options": {
								"raw": {
									"language": "json"
								}
							}
						},
						"url": {
							"raw": "http://localhost:3000/api/comments/67179500b44a8e1aff8e8193",
							"protocol": "http",
							"host": [
								"localhost"
							],
							"port": "3000",
							"path": [
								"api",
								"comments",
								"67179500b44a8e1aff8e8193"
							]
						}
					},
					"response": [
						{
							"name": "update Comment",
							"originalRequest": {
								"method": "PUT",
								"header": [],
								"body": {
									"mode": "raw",
									"raw": "{\r\n    \"text\": \"This A perfect content \",\r\n    \"video_id\": \"6713cf0791e13d01a30a0871\"\r\n}",
									"options": {
										"raw": {
											"language": "json"
										}
									}
								},
								"url": {
									"raw": "http://localhost:3000/api/comments/67179500b44a8e1aff8e8193",
									"protocol": "http",
									"host": [
										"localhost"
									],
									"port": "3000",
									"path": [
										"api",
										"comments",
										"67179500b44a8e1aff8e8193"
									]
								}
							},
							"status": "OK",
							"code": 200,
							"_postman_previewlanguage": "json",
							"header": [
								{
									"key": "X-Powered-By",
									"value": "Express"
								},
								{
									"key": "Content-Type",
									"value": "application/json; charset=utf-8"
								},
								{
									"key": "Content-Length",
									"value": "256"
								},
								{
									"key": "ETag",
									"value": "W/\"100-O0nCoRmlYuWkz96fCLIqS87Ywwc\""
								},
								{
									"key": "Date",
									"value": "Tue, 22 Oct 2024 12:38:01 GMT"
								},
								{
									"key": "Connection",
									"value": "keep-alive"
								},
								{
									"key": "Keep-Alive",
									"value": "timeout=5"
								}
							],
							"cookie": [],
							"body": "{\n    \"status\": \"success\",\n    \"data\": {\n        \"_id\": \"67179500b44a8e1aff8e8193\",\n        \"text\": \"This A perfect content \",\n        \"video_id\": \"6713cf0791e13d01a30a0871\",\n        \"user_id\": \"671788d8dc1ee558bc6811eb\",\n        \"createdAt\": \"2024-10-22T12:05:20.259Z\",\n        \"updatedAt\": \"2024-10-22T12:38:01.439Z\",\n        \"__v\": 0\n    }\n}"
						}
					]
				},
				{
					"name": "Delete Comment",
					"request": {
						"auth": {
							"type": "bearer",
							"bearer": [
								{
									"key": "token",
									"value": "eyJhbGciOiJIUzI1NiIsInR5cCI6IkpXVCJ9.eyJpZCI6IjY3MTc4OGQ4ZGMxZWU1NThiYzY4MTFlYiIsImlhdCI6MTcyOTU5OTk0NCwiZXhwIjoxNzI5NjAzNTQ0fQ.bXj82tFXdh01oXHjr-SE8faRvJg6xxGnqA45duGWdYQ",
									"type": "string"
								}
							]
						},
						"method": "DELETE",
						"header": [],
						"body": {
							"mode": "raw",
							"raw": "",
							"options": {
								"raw": {
									"language": "json"
								}
							}
						},
						"url": {
							"raw": "http://localhost:3000/api/comments/67179511b44a8e1aff8e8197",
							"protocol": "http",
							"host": [
								"localhost"
							],
							"port": "3000",
							"path": [
								"api",
								"comments",
								"67179511b44a8e1aff8e8197"
							]
						}
					},
					"response": [
						{
							"name": "Delete Comment",
							"originalRequest": {
								"method": "DELETE",
								"header": [],
								"body": {
									"mode": "raw",
									"raw": "",
									"options": {
										"raw": {
											"language": "json"
										}
									}
								},
								"url": {
									"raw": "http://localhost:3000/api/comments/67179511b44a8e1aff8e8197",
									"protocol": "http",
									"host": [
										"localhost"
									],
									"port": "3000",
									"path": [
										"api",
										"comments",
										"67179511b44a8e1aff8e8197"
									]
								}
							},
							"status": "OK",
							"code": 200,
							"_postman_previewlanguage": "json",
							"header": [
								{
									"key": "X-Powered-By",
									"value": "Express"
								},
								{
									"key": "Content-Type",
									"value": "application/json; charset=utf-8"
								},
								{
									"key": "Content-Length",
									"value": "20"
								},
								{
									"key": "ETag",
									"value": "W/\"14-Y53wuE/mmbSikKcT/WualL1N65U\""
								},
								{
									"key": "Date",
									"value": "Tue, 22 Oct 2024 12:40:54 GMT"
								},
								{
									"key": "Connection",
									"value": "keep-alive"
								},
								{
									"key": "Keep-Alive",
									"value": "timeout=5"
								}
							],
							"cookie": [],
							"body": "{\n    \"status\": \"success\"\n}"
						}
					]
				}
			]
		}
	]
}